reducto/__init__.py
reducto/cli.py
reducto/items.py
reducto/package.py
reducto/reducto.py
reducto/reports.py
reducto/src.py
reducto-1.0.3.dist-info/entry_points.txt
reducto-1.0.3.dist-info/LICENSE
reducto-1.0.3.dist-info/WHEEL
reducto-1.0.3.dist-info/METADATA
reducto-1.0.3.dist-info/RECORD
