Metadata-Version: 2.1
Name: reducto
Version: 1.0.3
Summary: Python source code stats in a command. 
Home-page: https://github.com/plaguss/reducto
License: MIT
Author: Agustín Piqueres
Author-email: agustin.piqueres@gmail.com
Requires-Python: >=3.8
Classifier: Intended Audience :: Developers
Classifier: License :: OSI Approved :: MIT License
Classifier: Programming Language :: Python :: 3.8
Requires-Dist: black ; extra == "dev"
Requires-Dist: mypy ; extra == "dev"
Requires-Dist: types-tabulate==0.8.2 ; extra == "dev"
Requires-Dist: tabulate==0.8.9 ; extra == "dev"
Requires-Dist: sphinx ; extra == "doc"
Requires-Dist: sphinx-rtd-theme ; extra == "doc"
Requires-Dist: tabulate==0.8.9 ; extra == "tabulate"
Requires-Dist: pytest==6.2.3 ; extra == "test"
Requires-Dist: pytest-cov==2.11.1 ; extra == "test"
Project-URL: Documentation, https://reducto.readthedocs.io
Project-URL: Repository, https://github.com/plaguss/reducto
Provides-Extra: dev
Provides-Extra: doc
Provides-Extra: tabulate
Provides-Extra: test
